pytmpfile/__init__.py
pytmpfile-0.2.0.dist-info/LICENSE
pytmpfile-0.2.0.dist-info/METADATA
pytmpfile-0.2.0.dist-info/WHEEL
pytmpfile-0.2.0.dist-info/top_level.txt
pytmpfile-0.2.0.dist-info/RECORD
