Metadata-Version: 2.1
Name: pytmpfile
Version: 0.2.0
Summary: Extremely simple helper for the memory-tempfile package
Home-page: https://github.com/jordiae/pytmpfile
License: MIT
Platform: UNKNOWN
Classifier: License :: OSI Approved :: MIT License
Classifier: Programming Language :: Python :: 3
Classifier: Programming Language :: Python :: 3.7
Classifier: Programming Language :: Python :: 3.8
Classifier: Programming Language :: Python :: 3.9
Classifier: Programming Language :: Python :: 3.0
License-File: LICENSE
Requires-Dist: memory-tempfile
